[
    {
        "asset_id": 349300102,
        "asset_name": "PIXELMOVE_01",
        "unit_name": "PXLMV01",
        "imageURL": "https://gateway.pinata.cloud/ipfs/QmY63YstW1V3AMHSwBdab8dw76UxJURxEJYZrD8uJPHF5e/"
    },
    {
        "asset_id": 349301876,
        "asset_name": "PIXELMOVE_02",
        "unit_name": "PXLMV02",
        "imageURL": "https://gateway.pinata.cloud/ipfs/QmbH97RhKgK9E3i8NhJpTtaoUUHFEhFE4B6vcK8mUoGPvW"
    },
    {
        "asset_id": 349303833,
        "asset_name": "PIXELMOVE_03",
        "unit_name": "PXLMV03",
        "imageURL": "https://gateway.pinata.cloud/ipfs/QmZJk8V21PKLnV4r1yB6hixu5wUnsFQxDV2tanbB4itZV1"
    },
    {
        "asset_id": 349305234,
        "asset_name": "PIXELMOVE_04",
        "unit_name": "PXLMV04",
        "imageURL": "https://gateway.pinata.cloud/ipfs/QmY3Eu5i6gXG3Fc8stZDn1XAqcoue93FHzKTwDKJxiddPK"
    },
    {
        "asset_id": 349306449,
        "asset_name": "PIXELMOVE_05",
        "unit_name": "PXLMV05",
        "imageURL": "https://gateway.pinata.cloud/ipfs/QmczdYVNmffQWfVFX6H4ERZBKgRQ8N4NrQmE57aAwZjZb2"
    },
    {
        "asset_id": 349308163,
        "asset_name": "PIXELMOVE_06",
        "unit_name": "PXLMV06",
        "imageURL": "https://gateway.pinata.cloud/ipfs/QmSjJDrXkfhi5cE5rxWni32tSB91ZuQqznggYu78qpqRzN"
    },
    {
        "asset_id": 349309818,
        "asset_name": "PIXELMOVE_07",
        "unit_name": "PXLMV07",
        "imageURL": "https://gateway.pinata.cloud/ipfs/QmYaMWtY9AN2ebDoeN5N9agGm21dV8rxj5G3CJtkwKp2bD"
    },
    {
        "asset_id": 349311199,
        "asset_name": "PIXELMOVE_08",
        "unit_name": "PXLMV08",
        "imageURL": "https://gateway.pinata.cloud/ipfs/Qmf6VorgeuopU3UoCb6TyDXpaAFD7RGJJAHFVtbNe3yecM/"
    },
    {
        "asset_id": 349312673,
        "asset_name": "PIXELMOVE_09",
        "unit_name": "PXLMV09",
        "imageURL": "https://gateway.pinata.cloud/ipfs/QmXywoA2zpWYeEECFnhypAc6UcmpqPuu7f1v2eqyQdmpWH/"
    },
    {
        "asset_id": 349314225,
        "asset_name": "PIXELMOVE_10",
        "unit_name": "PXLMV10",
        "imageURL": "https://gateway.pinata.cloud/ipfs/QmaUwBcwC35Hp4Ks3xVYUh48rt6r3e36Qgkpp8DTrfpXAj/"
    },
    {
        "asset_id": 349315575,
        "asset_name": "PIXELMOVE_11",
        "unit_name": "PXLMV11",
        "imageURL": "https://gateway.pinata.cloud/ipfs/QmeQWqVHuon9nTT6Wqn78B4aF9sAqMbE8Q7gVJJXEGorHx/"
    },
    {
        "asset_id": 349316912,
        "asset_name": "PIXELMOVE_12",
        "unit_name": "PXLMV12",
        "imageURL": "https://gateway.pinata.cloud/ipfs/QmaiGutqBrTLg52Fx5cyxSJ5JSD8dmE2ydZ2fCvCUMEHmE"
    },
    {
        "asset_id": 349318364,
        "asset_name": "PIXELMOVE_13",
        "unit_name": "PXLMV13",
        "imageURL": "https://gateway.pinata.cloud/ipfs/QmVNimnRPs5GQxSS6NVmCQfeMMyYHPuSjLVHYJN2SbR7pi"
    },
    {
        "asset_id": 349320082,
        "asset_name": "PIXELMOVE_14",
        "unit_name": "PXLMV14",
        "imageURL": "https://gateway.pinata.cloud/ipfs/QmZNwTcDZXNqDPGGyH3of1nPmkoqVKgvWqjuEjvovDYsTy"
    },
    {
        "asset_id": 349321267,
        "asset_name": "PIXELMOVE_15",
        "unit_name": "PXLMV15",
        "imageURL": "https://gateway.pinata.cloud/ipfs/QmSaQisS9vaMK9EUTp569R43pwJ4LCte9bbzANjTrLSGN4"
    },
    {
        "asset_id": 349322682,
        "asset_name": "PIXELMOVE_16",
        "unit_name": "PXLMV16",
        "imageURL": "https://gateway.pinata.cloud/ipfs/QmQCP2TQWH31TJcrNQichBSRipnxY1Pk6GY6tnSSZG5mKK"
    },
    {
        "asset_id": 349324133,
        "asset_name": "PIXELMOVE_17",
        "unit_name": "PXLMV17",
        "imageURL": "https://gateway.pinata.cloud/ipfs/QmXxwoj8dX3PwBcD4XyFMUFRuo32AeEBPcNT6ZL6ojovcv"
    },
    {
        "asset_id": 349328501,
        "asset_name": "PIXELMOVE_18",
        "unit_name": "PXLMV18",
        "imageURL": "https://gateway.pinata.cloud/ipfs/QmPxghiRPbh7W43iUERU87GvQvmfgKFQTLtkxBBNxWCJTY"
    },
    {
        "asset_id": 349329889,
        "asset_name": "PIXELMOVE_19",
        "unit_name": "PXLMV19",
        "imageURL": "https://gateway.pinata.cloud/ipfs/Qmf9s7g8MSEWExD5YAG49o9bWTLxnT1xGtw5JVg6GteZY4"
    },
    {
        "asset_id": 349332684,
        "asset_name": "PIXELMOVE_20",
        "unit_name": "PXLMV20",
        "imageURL": "https://gateway.pinata.cloud/ipfs/QmdLzsDSnqZ64sJseGjVwoh1wnsynGvjUjxor8hYU8VkeJ"
    },
    {
        "asset_id": 349333863,
        "asset_name": "PIXELMOVE_21",
        "unit_name": "PXLMV21",
        "imageURL": "https://gateway.pinata.cloud/ipfs/QmP4YZvUxUv7U9gAMd5KxEV2szDwaFS6YpDEePQYkXs3WW/"
    },
    {
        "asset_id": 349335038,
        "asset_name": "PIXELMOVE_22",
        "unit_name": "PXLMV22",
        "imageURL": "https://gateway.pinata.cloud/ipfs/QmbKTozoNvyJ19TznNsHqgaQ9p9sQ5g8KTGReWU5UEqDqh/"
    },
    {
        "asset_id": 349336091,
        "asset_name": "PIXELMOVE_23",
        "unit_name": "PXLMV23",
        "imageURL": "https://gateway.pinata.cloud/ipfs/QmRER34Lu9L2XPkTCHP2rSM4YVB5dz587cJWbmjtaizQ6o"
    },
    {
        "asset_id": 349337062,
        "asset_name": "PIXELMOVE_24",
        "unit_name": "PXLMV24",
        "imageURL": "https://gateway.pinata.cloud/ipfs/QmWYdCzUN4jZydocVL4UmHGxKafoBLHhFF1HCVk5SuHmzV/"
    },
    {
        "asset_id": 349338233,
        "asset_name": "PIXELMOVE_25",
        "unit_name": "PXLMV25",
        "imageURL": "https://gateway.pinata.cloud/ipfs/Qmcn2EXwkUMTK8nRQuy8M6YeXv4MXiyJe8bpF42k3YAgxE/"
    },
    {
        "asset_id": 349339579,
        "asset_name": "PIXELMOVE_26",
        "unit_name": "PXLMV26",
        "imageURL": "https://gateway.pinata.cloud/ipfs/QmeS1FMJx4N4oFrmkqVYZM8Qh31zLTTScMypH8HXJfiESR/"
    },
    {
        "asset_id": 349340695,
        "asset_name": "PIXELMOVE_27",
        "unit_name": "PXLMV27",
        "imageURL": "https://gateway.pinata.cloud/ipfs/Qmc2j1MKsFFV179u5CGoiWBMTZPoUUgBSACdudxe4r8HEn/"
    },
    {
        "asset_id": 349342007,
        "asset_name": "PIXELMOVE_28",
        "unit_name": "PXLMV28",
        "imageURL": "https://gateway.pinata.cloud/ipfs/QmPgJzgUG6fP2gokL4CAiDrrc8uaEmjDYauUHUKp2TLM1i"
    },
    {
        "asset_id": 349343263,
        "asset_name": "PIXELMOVE_29",
        "unit_name": "PXLMV29",
        "imageURL": "https://gateway.pinata.cloud/ipfs/QmSt612fwkj3NhzX1i9e4uxM2FW82JHoGethVpwSbf1Ewb"
    },
    {
        "asset_id": 349344444,
        "asset_name": "PIXELMOVE_30",
        "unit_name": "PXLMV30",
        "imageURL": "https://gateway.pinata.cloud/ipfs/QmSjVrXxhKY4aVHSzJS7YvsnoeQYGqw66fMWHyF4gdCkJt"
    },
    {
        "asset_id": 349345463,
        "asset_name": "PIXELMOVE_31",
        "unit_name": "PXLMV31",
        "imageURL": "https://gateway.pinata.cloud/ipfs/QmNPJWW9wjVBUcvNLvfuEV87xAziATsALjzGWVBjygL1cA"
    },
    {
        "asset_id": 349346542,
        "asset_name": "PIXELMOVE_32",
        "unit_name": "PXLMV32",
        "imageURL": "https://gateway.pinata.cloud/ipfs/Qmdsx9miuShLyo6hJcYZUD6mPGaWLi8tmV9WYV64cFrUVp"
    },
    {
        "asset_id": 349347826,
        "asset_name": "PIXELMOVE_33",
        "unit_name": "PXLMV33",
        "imageURL": "https://gateway.pinata.cloud/ipfs/QmfY6MgeR5BgR85LZYARTvykQghrpkD5eqPWALXBoLoEGy"
    },
    {
        "asset_id": 349351757,
        "asset_name": "PIXELMOVE_34",
        "unit_name": "PXLMV34",
        "imageURL": "https://gateway.pinata.cloud/ipfs/QmfXNKBzpNz8oo1VfgXxomSco6Abh4TLfQ4NMFEL1pBx9r"
    },
    {
        "asset_id": 349352904,
        "asset_name": "PIXELMOVE_35",
        "unit_name": "PXLMV35",
        "imageURL": "https://gateway.pinata.cloud/ipfs/QmYkfHUvdC3Nmte9Gf4ZCEhdSaQzzU1G6Jy1BB2n9zzBXH"
    },
    {
        "asset_id": 349354037,
        "asset_name": "PIXELMOVE_36",
        "unit_name": "PXLMV36",
        "imageURL": "https://gateway.pinata.cloud/ipfs/QmQLmqb1U9vfghCfuPHdzewXdnMLUQfELpSePXa9PqvXQV"
    },
    {
        "asset_id": 349355391,
        "asset_name": "PIXELMOVE_37",
        "unit_name": "PXLMV37",
        "imageURL": "https://gateway.pinata.cloud/ipfs/QmYvtG1gc6c23tcJ46ykFCBx4Jtcw1Gss8aDVBMFqwt1d9"
    },
    {
        "asset_id": 349356739,
        "asset_name": "PIXELMOVE_38",
        "unit_name": "PXLMV38",
        "imageURL": "https://gateway.pinata.cloud/ipfs/QmeNVDgqqina5ZeJp21EKeFcxGx2ou3ntcBJDeBY2RK5RS"
    },
    {
        "asset_id": 349357858,
        "asset_name": "PIXELMOVE_39",
        "unit_name": "PXLMV39",
        "imageURL": "https://gateway.pinata.cloud/ipfs/Qmexq82swCm72uzNNZNudfX997arXyRZgRxKesJkbyAYNN"
    },
    {
        "asset_id": 349359010,
        "asset_name": "PIXELMOVE_40",
        "unit_name": "PXLMV40",
        "imageURL": "https://gateway.pinata.cloud/ipfs/Qmdu6w9DfcxUJ7xM7pSXk5CQnFt4kVbU1HxaM3R8JN2mnF"
    },
    {
        "asset_id": 349360245,
        "asset_name": "PIXELMOVE_41",
        "unit_name": "PXLMV41",
        "imageURL": "https://gateway.pinata.cloud/ipfs/Qmf2UagTuwQPBNiFC558ZLDchVzr1uq8LABAaFnHUU6dcN/"
    },
    {
        "asset_id": 349361169,
        "asset_name": "PIXELMOVE_42",
        "unit_name": "PXLMV42",
        "imageURL": "https://gateway.pinata.cloud/ipfs/QmaTKdq3TaY88geP1vhB2oCqRxkVBTGvtGRg7QFScN5oJn/"
    },
    {
        "asset_id": 349362101,
        "asset_name": "PIXELMOVE_43",
        "unit_name": "PXLMV43",
        "imageURL": "https://gateway.pinata.cloud/ipfs/QmTPinAvNoxcUfQEvG4SfNqGDhHSNoTsGY1nH6cLe8FGwS/"
    },
    {
        "asset_id": 349363381,
        "asset_name": "PIXELMOVE_44",
        "unit_name": "PXLMV44",
        "imageURL": "https://gateway.pinata.cloud/ipfs/QmWuMSP2SAShhbvkQ9UkNKZmHbFVxWsa42xyRJjiXrr2KL/"
    },
    {
        "asset_id": 349364516,
        "asset_name": "PIXELMOVE_45",
        "unit_name": "PXLMV45",
        "imageURL": "https://gateway.pinata.cloud/ipfs/QmdaocSXhvQNHQANKgRFFdDBMXp5oetCJGrHyFikV3Ssz5/"
    },
    {
        "asset_id": 349365773,
        "asset_name": "PIXELMOVE_46",
        "unit_name": "PXLMV46",
        "imageURL": "https://gateway.pinata.cloud/ipfs/QmNUxGuWKwPTkRK8SV5bVMCEdUu38jeqGDxSeJ64FbAwuZ/"
    },
    {
        "asset_id": 349367031,
        "asset_name": "PIXELMOVE_47",
        "unit_name": "PXLMV47",
        "imageURL": "https://gateway.pinata.cloud/ipfs/QmUzNGyki4eeHZi6hLSi9d2qbDQDRVprrg5N8xXSDjoRLe/"
    },
    {
        "asset_id": 349368211,
        "asset_name": "PIXELMOVE_48",
        "unit_name": "PXLMV48",
        "imageURL": "https://gateway.pinata.cloud/ipfs/QmUf2udfYAFfRbcgQtz2aURUBXLDoL4xYVJF4LneWpcHN1/"
    }
]